ctd/__init__.py
ctd/get_data.py
ctd/utils.py
ctd_python-0.2.1.dist-info/METADATA
ctd_python-0.2.1.dist-info/WHEEL
ctd_python-0.2.1.dist-info/top_level.txt
ctd_python-0.2.1.dist-info/RECORD
