Metadata-Version: 2.1
Name: ctd-python
Version: 0.2.1
Summary: Python interface to access data from The Comparative Toxicogenomics Database (CTD)
Home-page: UNKNOWN
License: UNKNOWN
Platform: UNKNOWN
Requires-Dist: requests
Requires-Dist: pandas
Requires-Dist: tqdm
